tox_uv/__init__.py
tox_uv/_installer.py
tox_uv/_package.py
tox_uv/_package_types.py
tox_uv/_run.py
tox_uv/_run_lock.py
tox_uv/_venv.py
tox_uv/_venv_query.py
tox_uv/plugin.py
tox_uv/py.typed
tox_uv/version.py
tox_uv-1.28.1.dist-info/METADATA
tox_uv-1.28.1.dist-info/WHEEL
tox_uv-1.28.1.dist-info/entry_points.txt
tox_uv-1.28.1.dist-info/licenses/LICENSE
tox_uv-1.28.1.dist-info/RECORD
