Metadata-Version: 2.4
Name: tox-uv
Version: 1.28.1
Summary: Integration of uv with tox.
Project-URL: Changelog, https://github.com/tox-dev/tox-uv/releases
Project-URL: Documentation, https://github.com/tox-dev/tox-uv#tox-uv
Project-URL: Homepage, https://github.com/tox-dev/tox-uv
Project-URL: Source, https://github.com/tox-dev/tox-uv
Project-URL: Tracker, https://github.com/tox-dev/tox-uv/issues
Maintainer-email: Bernát Gábor <gaborjbernat@gmail.com>
License-Expression: MIT
License-File: LICENSE
Keywords: environments,isolated,testing,virtual
Classifier: Development Status :: 5 - Production/Stable
Classifier: Intended Audience :: Developers
Classifier: Operating System :: OS Independent
Classifier: Programming Language :: Python
Classifier: Programming Language :: Python :: 3 :: Only
Classifier: Programming Language :: Python :: 3.9
Classifier: Programming Language :: Python :: 3.10
Classifier: Programming Language :: Python :: 3.11
Classifier: Programming Language :: Python :: 3.12
Classifier: Programming Language :: Python :: 3.13
Classifier: Topic :: Internet
Classifier: Topic :: Software Development :: Libraries
Classifier: Topic :: System
Requires-Python: >=3.9
Requires-Dist: packaging>=25
Requires-Dist: tomli>=2.2.1; python_version < '3.11'
Requires-Dist: tox<5,>=4.30.2
Requires-Dist: typing-extensions>=4.15; python_version < '3.10'
Requires-Dist: uv<1,>=0.8.16
